Workbook

Sheet Raw_data
A1: Order_ID | B1: Order_Date | C1: Customer_ID | D1: Customer_Type | E1: Region | F1: Category | G1: Product | H1: Quantity | I1: Unit_Price | J1: Discount | K1: Sales | L1: Profit | M1: Payment_Method | N1: Order_Status
A2: NX1001 | B2: 45660 | C2: C101 | D2: New | E2: North | F2: Electronics | G2: Wireless Earbuds | H2: 2 | I2: 2499 | J2: 0.05 | K2: 4748.1 | L2: 759.7 | M2: UPI | N2: Delivered
A3: NX1002 | B3: 45662 | C3: C102 | D3: Returning | E3: West | F3: Home | G3: Ceramic Coffee Mug Set | H3: 3 | I3: 799 | J3: 0 | K3: 2397 | L3: 647.19 | M3: Card | N3: Delivered
A4: NX1003 | B4: 45665 | C4: C103 | D4: New | E4: South | F4: Fashion | G4: Cotton Oversized T-Shirt | H4: 2 | I4: 899 | J4: 0.1 | K4: 1618.2 | L4: 485.46 | M4: UPI | N4: Delivered
A5: NX1004 | B5: 45669 | C5: C104 | D5: Returning | E5: East | F5: Beauty | G5: Skin Care Gift Box | H5: 1 | I5: 1899 | J5: 0.05 | K5: 1804.05 | L5: 577.3 | M5: Wallet | N5: Delivered
A6: NX1005 | B6: 45673 | C6: C105 | D6: New | E6: North | F6: Sports | G6: Yoga Mat Pro | H6: 1 | I6: 1499 | J6: 0 | K6: 1499 | L6: 524.65 | M6: COD | N6: Delivered
A7: NX1006 | B7: 45676 | C7: C106 | D7: Returning | E7: West | F7: Electronics | G7: Smart Watch Lite | H7: 1 | I7: 3499 | J7: 0.1 | K7: 3149.1 | L7: 566.84 | M7: Card | N7: Delivered
A8: NX1007 | B8: 45679 | C8: C107 | D8: New | E8: South | F8: Home | G8: LED Desk Lamp | H8: 2 | I8: 1299 | J8: 0.05 | K8: 2468.1 | L8: 740.43 | M8: UPI | N8: Delivered
A9: NX1008 | B9: 45683 | C9: C108 | D9: Returning | E9: North | F9: Fashion | G9: Everyday Sneakers | H9: 1 | I9: 2299 | J9: 0.15 | K9: 1954.15 | L9: 488.54 | M9: Card | N9: Returned
A10: NX1009 | B10: 45686 | C10: C109 | D10: New | E10: East | F10: Beauty | G10: Vitamin C Serum | H10: 2 | I10: 699 | J10: 0 | K10: 1398 | L10: 559.2 | M10: UPI | N10: Delivered
A11: NX1010 | B11: 45690 | C11: C110 | D11: Returning | E11: West | F11: Electronics | G11: Portable Bluetooth Speaker | H11: 1 | I11: 2199 | J11: 0.05 | K11: 2089.05 | L11: 605.82 | M11: Wallet | N11: Delivered
A12: NX1011 | B12: 45692 | C12: C111 | D12: New | E12: North | F12: Home | G12: Storage Organizer Set | H12: 4 | I12: 599 | J12: 0 | K12: 2396 | L12: 718.8 | M12: UPI | N12: Delivered
A13: NX1012 | B13: 45695 | C13: C112 | D13: Returning | E13: South | F13: Sports | G13: Resistance Band Kit | H13: 2 | I13: 899 | J13: 0.1 | K13: 1618.2 | L13: 566.37 | M13: Card | N13: Delivered
... A81: NX1080 | B81: 45902 | C81: C180 | D81: Returning | E81: North | F81: Electronics | G81: Smart Watch Lite | H81: 1 | I81: 3499 | J81: 0.2 | K81: 2799.2 | L81: 503.86 | M81: Wallet | N81: Delivered

Sheet Analysis
A1: Sohacart sales analysis
A3: Total sales | B3: =SUM(Raw_data!K2:K81) -> 193266.75
A4: Total profit | B4: =SUM(Raw_data!L2:L81) -> 52027.71
A5: Total Quantity sold | B5: =SUM(Raw_data!H2:H81) -> 132
A6: Average Order Value | B6: =AVERAGE(Raw_data!K2:K81) -> 2415.8344
A9: Category | B9: Total sales | D9: Category | E9: Total Profit
A10: Electronics | B10: =SUMIF(Raw_data!F2:F81,A10,Raw_data!K2:K81) -> 50437.15 | D10: Electronics | E10: =SUMIF(Raw_data!F2:F81,D10,Raw_data!L2:L81) -> 11737.72
A11: Home | B11: =SUMIF(Raw_data!F3:F82,A11,Raw_data!K3:K82) -> 38812.45 | D11: Home | E11: =SUMIF(Raw_data!F3:F82,D11,Raw_data!L3:L82) -> 10466.02
A12: Fashion | B12: =SUMIF(Raw_data!F4:F83,A12,Raw_data!K4:K83) -> 34430.55 | D12: Fashion | E12: =SUMIF(Raw_data!F4:F83,D12,Raw_data!L4:L83) -> 9243.38
A13: Beauty | B13: =SUMIF(Raw_data!F5:F84,A13,Raw_data!K5:K84) -> 29953.3 | D13: Beauty | E13: =SUMIF(Raw_data!F5:F84,D13,Raw_data!L5:L84) -> 9947.51
A14: Sports | B14: =SUMIF(Raw_data!F6:F85,A14,Raw_data!K6:K85) -> 39633.3 | D14: Sports | E14: =SUMIF(Raw_data!F6:F85,D14,Raw_data!L6:L85) -> 10633.08
A17: Region | B17: Total sales | D17: Customer Type | E17: Total sales
A18: North | B18: =SUMIF(Raw_data!E2:E81,A18,Raw_data!K2:K81) -> 51658.3 | D18: New | E18: =SUMIF(Raw_data!D2:D81,D18,Raw_data!K2:K81) -> 92860.35
A19: South | B19: =SUMIF(Raw_data!E3:E82,A19,Raw_data!K3:K82) -> 51872 | D19: Returning | E19: =SUMIF(Raw_data!D3:D82,D19,Raw_data!K3:K82) -> 100406.4
A20: East | B20: =SUMIF(Raw_data!E4:E83,A20,Raw_data!K4:K83) -> 42180.95
A21: West | B21: =SUMIF(Raw_data!E5:E84,A21,Raw_data!K5:K84) -> 45158.5
A24: Order status | B24: Number of orders | D24: Payment method | E24: No of orders
A25: Delivered | B25: =COUNTIF(Raw_data!N2:N81,A25) -> 74 | D25: UPI | E25: =COUNTIF(Raw_data!M2:M81,D25) -> 28
A26: Returned | B26: =COUNTIF(Raw_data!N3:N82,A26) -> 4 | D26: Card | E26: =COUNTIF(Raw_data!M3:M82,D26) -> 27
A27: Cancelled | B27: =COUNTIF(Raw_data!N4:N83,A27) -> 2 | D27: COD | E27: =COUNTIF(Raw_data!M4:M83,D27) -> 12
D28: Wallet | E28: =COUNTIF(Raw_data!M5:M84,D28) -> 13

Sheet Dashboard
A1: Sohacart sales dashboard
A3: Total sales | D3: Total Profit | G3: Units sold | J3: Average order value
A4: =Analysis!B3 -> 193266.75 | D4: =Analysis!B4 -> 52027.71 | G4: =Analysis!B5 -> 132 | J4: =Analysis!B6 -> 2415.8344
